[
    {
        "word": "sich verabschieden",
        "language": "German"
    },
    {
        "word": "zuerst",
        "language": "German"
    },
    {
        "word": "auf",
        "language": "German"
    },
    {
        "word": "Lastwagen",
        "language": "German"
    },
    {
        "word": "unter",
        "language": "German"
    },
    {
        "word": "zerbrechlich",
        "language": "German"
    },
    {
        "word": "Was fúr elegante Schuhe!",
        "language": "German"
    },
    {
        "word": "Was fúr ein guter Geschmack!",
        "language": "German"
    },
    {
        "word": "Glaubst du (wirklich)?",
        "language": "German"
    },
    {
        "word": "so viele",
        "language": "German"
    },
    {
        "word": "Findest du?",
        "language": "German"
    },
    {
        "word": "die Wahrheit",
        "language": "German"
    }
]